{"mtime": 1783335712.58, "classes": [{"type_id": "1", "type_name": "\u65e5\u97e9\u65e0\u7801"}, {"type_id": "2", "type_name": "\u56fd\u4ea7\u7cbe\u54c1"}, {"type_id": "3", "type_name": "\u65e5\u97e9\u7cbe\u54c1"}, {"type_id": "4", "type_name": "\u6b27\u7f8e\u7cbe\u54c1"}, {"type_id": "5", "type_name": "\u81ea\u62cd\u5077\u62cd"}, {"type_id": "6", "type_name": "\u4e2d\u6587\u5b57\u5e55"}, {"type_id": "7", "type_name": "\u4eba\u59bb\u7cfb\u5217"}, {"type_id": "8", "type_name": "\u5236\u670d\u8bf1\u60d1"}, {"type_id": "9", "type_name": "\u5f3a\u5978\u4e71\u4f26"}, {"type_id": "10", "type_name": "AV\u660e\u661f"}, {"type_id": "11", "type_name": "\u56fd\u4ea7\u4f20\u5a92"}, {"type_id": "12", "type_name": "\u5de8\u4e73\u7cfb\u5217"}, {"type_id": "13", "type_name": "\u989c\u5c04\u7cfb\u5217"}, {"type_id": "14", "type_name": "\u81ea\u6170\u7cfb\u5217"}]}